am4utils/libduckdb.so
am4utils/py.typed
am4utils/__init__.py
am4utils/_core.cpython-310-x86_64-linux-gnu.so
am4utils/__init__.pyi
am4utils/demand/__init__.py
am4utils/aircraft/__init__.py
am4utils/db/__init__.py
am4utils/api/__init__.py
am4utils/api/models/user.py
am4utils/api/models/core.py
am4utils/api/models/alliance.py
am4utils/route/__init__.py
am4utils/game/__init__.py
am4utils/_core/__init__.pyi
am4utils/_core/demand/__init__.pyi
am4utils/_core/aircraft/__init__.pyi
am4utils/_core/db/__init__.pyi
am4utils/_core/route/__init__.pyi
am4utils/_core/game/__init__.pyi
am4utils/_core/log/__init__.pyi
am4utils/_core/airport/__init__.pyi
am4utils/_core/ticket/__init__.pyi
am4utils/log/__init__.py
am4utils/airport/__init__.py
am4utils/ticket/__init__.py
am4utils-0.1.7.dist-info/WHEEL
am4utils-0.1.7.dist-info/RECORD
am4utils-0.1.7.dist-info/METADATA
am4utils-0.1.7.dist-info/entry_points.txt
am4utils-0.1.7.dist-info/licenses/LICENSE
