Metadata-Version: 2.1
Name: am4utils
Version: 0.1.7
Summary: Tools and utilities for the game Airline Manager 4.
Author-Email: cathaypacific8747 <58929011+cathaypacific8747@users.noreply.github.com>
License: MIT License
Classifier: Development Status :: 4 - Beta
Classifier: License :: OSI Approved :: MIT License
Classifier: Programming Language :: Python :: 3 :: Only
Classifier: Programming Language :: Python :: 3.11
Classifier: Programming Language :: Python :: 3.10
Classifier: Programming Language :: Python :: 3.9
Requires-Python: >=3.9
Requires-Dist: httpx>=0.24.1
Requires-Dist: pydantic>=2.1.1
Requires-Dist: pybind11; extra == "dev"
Requires-Dist: pybind11-stubgen; extra == "dev"
Requires-Dist: pytest; extra == "dev"
Requires-Dist: pytest-asyncio; extra == "dev"
Provides-Extra: dev
